MarkerCount/__init__.py
MarkerCount/hicat.py
MarkerCount/marker_count.py
MarkerCount-0.7.1.dist-info/LICENSE
MarkerCount-0.7.1.dist-info/METADATA
MarkerCount-0.7.1.dist-info/WHEEL
MarkerCount-0.7.1.dist-info/entry_points.txt
MarkerCount-0.7.1.dist-info/top_level.txt
MarkerCount-0.7.1.dist-info/RECORD
