Metadata-Version: 2.1
Name: MarkerCount
Version: 0.7.1
Summary: Cell-type identification toolkit for single-cell RNA-Seq experiments.
Author-email: Seokhyun Yoon <syoon@dku.edu>
License: MIT License
Project-URL: Homepage, https://github.com/combio-dku/
Project-URL: repository, https://github.com/combio-dku/HiCAT
Keywords: single-cell omics,bioinformatics
Classifier: Programming Language :: Python
Classifier: Programming Language :: Python :: 3
Classifier: License :: OSI Approved :: MIT License
License-File: LICENSE
Provides-Extra: dev
Requires-Dist: numpy; extra == "dev"
Requires-Dist: pandas; extra == "dev"
Requires-Dist: scipy; extra == "dev"
Requires-Dist: scikit-learn; extra == "dev"
Requires-Dist: scikit-network; extra == "dev"
